MANIFEST.in
README_pytq.md
pyproject.toml
setup.py
_yatq/bind.cpp
_yatq/traits.h
_yatq/include/yatq/thread_pool.h
_yatq/include/yatq/timer_queue.h
_yatq/include/yatq/version.h
_yatq/include/yatq/internal/concepts.h
_yatq/include/yatq/internal/log4cxx_proxy.h
_yatq/include/yatq/internal/promise_utils.h
_yatq/include/yatq/utils/logging_utils.h
_yatq/include/yatq/utils/sched_utils.h
pytq/__init__.py
pytq/pythonize.py
pytq_cxx.egg-info/PKG-INFO
pytq_cxx.egg-info/SOURCES.txt
pytq_cxx.egg-info/dependency_links.txt
pytq_cxx.egg-info/top_level.txt
setup_helpers/find_dep_headers.cmake
setup_helpers/find_dep_libs.cmake