Metadata-Version: 2.4
Name: pytq-cxx
Version: 1.1.0
Summary: single-threaded timer demultiplexer backed by C++ implementation
Author-email: Nikita Vaganov <nikita.e.vaganov@gmail.com>
Project-URL: Homepage, https://github.com/vaganov/yatq
Project-URL: Bug Tracker, https://github.com/vaganov/yatq/issues
Classifier: Programming Language :: Python :: 3
Classifier: License :: OSI Approved :: GNU Lesser General Public License v3 (LGPLv3)
Requires-Python: >=3.7
